setup.py
subtitle_downloader/__init__.py
subtitle_downloader/subtitle.py
subtitle_fetcher.egg-info/PKG-INFO
subtitle_fetcher.egg-info/SOURCES.txt
subtitle_fetcher.egg-info/dependency_links.txt
subtitle_fetcher.egg-info/entry_points.txt
subtitle_fetcher.egg-info/pbr.json
subtitle_fetcher.egg-info/top_level.txt