Metadata-Version: 1.1
Name: subtitle-fetcher
Version: 0.1.0
Summary: Python tool to download subtitles.
Home-page: https://github.com/ajayrfhp/subtitle-fetcher/
Author: Ajay Prasadh V
Author-email: ajayrfhp1710@gmail.com
License: UNKNOWN
Keywords: subtitle,download,utility,movie
Platform: UNKNOWN
Classifier: Operating System :: POSIX
Classifier: Programming Language :: Python
Classifier: Programming Language :: Python :: 2
Classifier: Programming Language :: Python :: 2.7
Classifier: Topic :: Utilities
